rtl/uart_rx.v
module uart_rx #(
    parameter CLKS_PER_BIT = 10
)(
    input  wire       clk,
    input  wire       reset,
    input  wire       rx,

    output reg [7:0]  rx_data,
    output reg        rx_valid,
    output reg        rx_busy
);

    localparam IDLE      = 2'd0;
    localparam START_BIT = 2'd1;
    localparam DATA_BITS = 2'd2;
    localparam STOP_BIT  = 2'd3;

    reg [1:0]  state;
    reg [15:0] clk_count;
    reg [2:0]  bit_index;

    always @(posedge clk) begin

        if (reset) begin
            state     <= IDLE;
            clk_count <= 0;
            bit_index <= 0;
            rx_data   <= 8'h00;
            rx_valid  <= 1'b0;
            rx_busy   <= 1'b0;
        end

        else begin

            rx_valid <= 1'b0;

            case (state)

                IDLE: begin
                    rx_busy   <= 1'b0;
                    clk_count <= 0;
                    bit_index <= 0;

                    if (rx == 1'b0) begin
                        rx_busy   <= 1'b1;
                        clk_count <= 0;
                        state     <= START_BIT;
                    end
                end

                START_BIT: begin
                    if (clk_count == (CLKS_PER_BIT/2 - 1)) begin
                        clk_count <= 0;

                        if (rx == 1'b0)
                            state <= DATA_BITS;
                        else
                            state <= IDLE;
                    end
                    else begin
                        clk_count <= clk_count + 1'b1;
                    end
                end

                DATA_BITS: begin
                    if (clk_count == CLKS_PER_BIT - 1) begin
                        clk_count <= 0;

                        rx_data[bit_index] <= rx;

                        if (bit_index == 3'd7) begin
                            bit_index <= 0;
                            state <= STOP_BIT;
                        end
                        else begin
                            bit_index <= bit_index + 1'b1;
                        end
                    end
                    else begin
                        clk_count <= clk_count + 1'b1;
                    end
                end

                STOP_BIT: begin
                    if (clk_count == CLKS_PER_BIT - 1) begin
                        clk_count <= 0;
                        rx_busy   <= 1'b0;
                        rx_valid  <= 1'b1;
                        state     <= IDLE;
                    end
                    else begin
                        clk_count <= clk_count + 1'b1;
                    end
                end

                default: begin
                    state <= IDLE;
                end

            endcase
        end
    end

endmodule

rtl/uart_tx.v
module uart_tx #(
    parameter CLK_FREQ  = 50_000_000,
    parameter BAUD_RATE = 9600
)(
    input  wire       clk,
    input  wire       reset,
    input  wire       tx_start,
    input  wire [7:0] tx_data,

    output reg        tx,
    output reg        tx_busy
);

    // Number of clock cycles required for one UART bit
    localparam CLKS_PER_BIT = CLK_FREQ / BAUD_RATE;

    reg [15:0] baud_counter;
    reg [3:0]  bit_index;
    reg [7:0]  data_reg;

    // UART states
    localparam IDLE  = 2'b00;
    localparam START = 2'b01;
    localparam DATA  = 2'b10;
    localparam STOP  = 2'b11;

    reg [1:0] state;

    always @(posedge clk) begin

        if (reset) begin
            tx           <= 1'b1;
            tx_busy      <= 1'b0;
            baud_counter <= 16'd0;
            bit_index    <= 4'd0;
            data_reg     <= 8'd0;
            state        <= IDLE;
        end

        else begin

            case (state)

                // ---------------- IDLE ----------------
                IDLE: begin
                    tx           <= 1'b1;
                    tx_busy      <= 1'b0;
                    baud_counter <= 16'd0;
                    bit_index    <= 4'd0;

                    if (tx_start) begin
                        data_reg <= tx_data;
                        tx_busy  <= 1'b1;
                        state    <= START;
                    end
                end

                // ---------------- START ----------------
                START: begin
                    tx <= 1'b0;

                    if (baud_counter < CLKS_PER_BIT - 1) begin
                        baud_counter <= baud_counter + 1;
                    end
                    else begin
                        baud_counter <= 0;
                        state        <= DATA;
                    end
                end

                // ---------------- DATA ----------------
                DATA: begin
                    tx <= data_reg[bit_index];

                    if (baud_counter < CLKS_PER_BIT - 1) begin
                        baud_counter <= baud_counter + 1;
                    end
                    else begin
                        baud_counter <= 0;

                        if (bit_index < 7) begin
                            bit_index <= bit_index + 1;
                        end
                        else begin
                            bit_index <= 0;
                            state     <= STOP;
                        end
                    end
                end

                // ---------------- STOP ----------------
                STOP: begin
                    tx <= 1'b1;

                    if (baud_counter < CLKS_PER_BIT - 1) begin
                        baud_counter <= baud_counter + 1;
                    end
                    else begin
                        baud_counter <= 0;
                        tx_busy      <= 1'b0;
                        state        <= IDLE;
                    end
                end

            endcase
        end
    end
endmodule

tb/uart_simulation_tb.v
`timescale 1ns/1ps

module uart_simulation_tb;

    // ==========================================
    // UART PARAMETERS
    // ==========================================
    parameter CLK_FREQ = 1_000_000;
    parameter BAUD_RATE = 100_000;
    parameter CLKS_PER_BIT = CLK_FREQ / BAUD_RATE;

    // ==========================================
    // TESTBENCH SIGNALS
    // ==========================================
    reg clk;
    reg reset;

    reg tx_start;
    reg [7:0] tx_data;

    wire tx;
    wire tx_busy;

    wire [7:0] rx_data;
    wire rx_valid;
    wire rx_busy;

    // Loopback connection
    wire rx;
    assign rx = tx;

    integer pass_count;
    integer fail_count;

    // ==========================================
    // UART TRANSMITTER
    // ==========================================
    uart_tx #(
        .CLK_FREQ(CLK_FREQ),
        .BAUD_RATE(BAUD_RATE)
    ) transmitter (
        .clk(clk),
        .reset(reset),
        .tx_start(tx_start),
        .tx_data(tx_data),
        .tx(tx),
        .tx_busy(tx_busy)
    );

    // ==========================================
    // UART RECEIVER
    // ==========================================
    uart_rx #(
        .CLKS_PER_BIT(CLKS_PER_BIT)
    ) receiver (
        .clk(clk),
        .reset(reset),
        .rx(rx),
        .rx_data(rx_data),
        .rx_valid(rx_valid),
        .rx_busy(rx_busy)
    );

    // ==========================================
    // CLOCK
    // 1 MHz clock = 1000 ns period
    // ==========================================
    always #500 clk = ~clk;

    // ==========================================
    // SEND BYTE TASK
    // ==========================================
    task send_byte;
        input [7:0] data;

        begin
            // Wait until transmitter is free
            wait(tx_busy == 1'b0);

            // Put data on TX
            tx_data = data;

            // Start transmission
            @(posedge clk);
            tx_start = 1'b1;

            @(posedge clk);
            tx_start = 1'b0;

            // Wait for receiver to finish
            wait(rx_valid == 1'b1);

            // Check received data
            if (rx_data == data) begin
                pass_count = pass_count + 1;

                $display(
                    "PASS: Sent = 0x%02h, Received = 0x%02h",
                    data,
                    rx_data
                );
            end
            else begin
                fail_count = fail_count + 1;

                $display(
                    "FAIL: Sent = 0x%02h, Received = 0x%02h",
                    data,
                    rx_data
                );
            end

            // Wait until rx_valid goes low
            @(posedge clk);

            // Small gap before next byte
            repeat(2) @(posedge clk);
        end
    endtask

    // ==========================================
    // MAIN TEST
    // ==========================================
    initial begin

        // VCD waveform
        $dumpfile("simulation/uart_simulation.vcd");
        $dumpvars(0, uart_simulation_tb);

        // Initial values
        clk = 1'b0;
        reset = 1'b1;
        tx_start = 1'b0;
        tx_data = 8'h00;

        pass_count = 0;
        fail_count = 0;

        // Reset
        repeat(5) @(posedge clk);
        reset = 1'b0;

        $display("");
        $display("==========================================");
        $display("       UART TX -> RX LOOPBACK TEST");
        $display("==========================================");
        $display("");

        // ======================================
        // TEST BYTES
        // ======================================

        $display("Sending byte 1: 0x41 (ASCII A)");
        send_byte(8'h41);

        $display("Sending byte 2: 0x55");
        send_byte(8'h55);

        $display("Sending byte 3: 0xAA");
        send_byte(8'hAA);

        $display("Sending byte 4: 0x00");
        send_byte(8'h00);

        $display("Sending byte 5: 0xFF");
        send_byte(8'hFF);

        $display("Sending byte 6: 0x7E");
        send_byte(8'h7E);

        // ======================================
        // TEST SUMMARY
        // ======================================

        $display("");
        $display("==========================================");
        $display("             TEST SUMMARY");
        $display("==========================================");

        $display("PASS COUNT = %0d", pass_count);
        $display("FAIL COUNT = %0d", fail_count);

        if (fail_count == 0) begin
            $display("");
            $display("UART LOOPBACK TEST: SUCCESS");
        end
        else begin
            $display("");
            $display("UART LOOPBACK TEST: FAILED");
        end

        $display("==========================================");
        $display("");

        $finish;
    end

endmodule

simulation/uart_simulation.vcd
$date
	Sun Aug 23 09:29:37 2026
$end
$version
	Icarus Verilog
$end
$timescale
	1ps
$end
$scope module uart_simulation_tb $end
$var wire 1 ! rx $end
$var wire 1 " tx_busy $end
$var wire 1 # tx $end
$var wire 1 $ rx_valid $end
$var wire 8 % rx_data [7:0] $end
$var wire 1 & rx_busy $end
$var parameter 32 ' BAUD_RATE $end
$var parameter 32 ( CLKS_PER_BIT $end
$var parameter 32 ) CLK_FREQ $end
$var reg 1 * clk $end
$var reg 1 + reset $end
$var reg 8 , tx_data [7:0] $end
$var reg 1 - tx_start $end
$var integer 32 . fail_count [31:0] $end
$var integer 32 / pass_count [31:0] $end
$scope module receiver $end
$var wire 1 * clk $end
$var wire 1 + reset $end
$var wire 1 ! rx $end
$var parameter 32 0 CLKS_PER_BIT $end
$var parameter 2 1 DATA_BITS $end
$var parameter 2 2 IDLE $end
$var parameter 2 3 START_BIT $end
$var parameter 2 4 STOP_BIT $end
$var reg 3 5 bit_index [2:0] $end
$var reg 16 6 clk_count [15:0] $end
$var reg 1 & rx_busy $end
$var reg 8 7 rx_data [7:0] $end
$var reg 1 $ rx_valid $end
$var reg 2 8 state [1:0] $end
$upscope $end
$scope module transmitter $end
$var wire 1 * clk $end
$var wire 1 + reset $end
$var wire 8 9 tx_data [7:0] $end
$var wire 1 - tx_start $end
$var parameter 32 : BAUD_RATE $end
$var parameter 32 ; CLKS_PER_BIT $end
$var parameter 32 < CLK_FREQ $end
$var parameter 2 = DATA $end
$var parameter 2 > IDLE $end
$var parameter 2 ? START $end
$var parameter 2 @ STOP $end
$var reg 16 A baud_counter [15:0] $end
$var reg 4 B bit_index [3:0] $end
$var reg 8 C data_reg [7:0] $end
$var reg 2 D state [1:0] $end
$var reg 1 # tx $end
$var reg 1 " tx_busy $end
$upscope $end
$scope task send_byte $end
$var reg 8 E data [7:0] $end
$upscope $end
$upscope $end
$enddefinitions $end
$comment Show the parameter values. $end
$dumpall
b11 @
b1 ?
b0 >
b10 =
b11110100001001000000 <
b1010 ;
b11000011010100000 :
b11 4
b1 3
b0 2
b10 1
b1010 0
b11110100001001000000 )
b1010 (
b11000011010100000 '
$end
#0
$dumpvars
bx E
bx D
bx C
bx B
bx A
b0 9
bx 8
bx 7
bx 6
bx 5
b0 /
b0 .
0-
b0 ,
1+
0*
x&
bx %
x$
x#
x"
x!
$end
#500000
b0 D
b0 C
b0 B
b0 A
0"
1!
1#
0&
0$
b0 %
b0 7
b0 5
b0 6
b0 8
1*
#1000000
0*
#1500000
1*
#2000000
0*
#2500000
1*
#3000000
0*
#3500000
1*
#4000000
0*
#4500000
b1000001 ,
b1000001 9
b1000001 E
0+
1*
#5000000
0*
#5500000
b1 D
1"
b1000001 C
1-
1*
#6000000
0*
#6500000
b1 A
0!
0#
0-
1*
#7000000
0*
#7500000
b1 8
1&
b10 A
1*
#8000000
0*
#8500000
b11 A
b1 6
1*
#9000000
0*
#9500000
b10 6
b100 A
1*
#10000000
0*
#10500000
b101 A
b11 6
1*
#11000000
0*
#11500000
b100 6
b110 A
1*
#12000000
0*
#12500000
b111 A
b10 8
b0 6
1*
#13000000
0*
#13500000
b1 6
b1000 A
1*
#14000000
0*
#14500000
b1001 A
b10 6
1*
#15000000
0*
#15500000
b11 6
b10 D
b0 A
1*
#16000000
0*
#16500000
b1 A
1!
1#
b100 6
1*
#17000000
0*
#17500000
b101 6
b10 A
1*
#18000000
0*
#18500000
b11 A
b110 6
1*
#19000000
0*
#19500000
b111 6
b100 A
1*
#20000000
0*
#20500000
b101 A
b1000 6
1*
#21000000
0*
#21500000
b1001 6
b110 A
1*
#22000000
0*
#22500000
b111 A
b1 5
b1 %
b1 7
b0 6
1*
#23000000
0*
#23500000
b1 6
b1000 A
1*
#24000000
0*
#24500000
b1001 A
b10 6
1*
#25000000
0*
#25500000
b11 6
b1 B
b0 A
1*
#26000000
0*
#26500000
b1 A
0!
0#
b100 6
1*
#27000000
0*
#27500000
b101 6
b10 A
1*
#28000000
0*
#28500000
b11 A
b110 6
1*
#29000000
0*
#29500000
b111 6
b100 A
1*
#30000000
0*
#30500000
b101 A
b1000 6
1*
#31000000
0*
#31500000
b1001 6
b110 A
1*
#32000000
0*
#32500000
b111 A
b10 5
b0 6
1*
#33000000
0*
#33500000
b1 6
b1000 A
1*
#34000000
0*
#34500000
b1001 A
b10 6
1*
#35000000
0*
#35500000
b11 6
b10 B
b0 A
1*
#36000000
0*
#36500000
b1 A
b100 6
1*
#37000000
0*
#37500000
b101 6
b10 A
1*
#38000000
0*
#38500000
b11 A
b110 6
1*
#39000000
0*
#39500000
b111 6
b100 A
1*
#40000000
0*
#40500000
b101 A
b1000 6
1*
#41000000
0*
#41500000
b1001 6
b110 A
1*
#42000000
0*
#42500000
b111 A
b11 5
b0 6
1*
#43000000
0*
#43500000
b1 6
b1000 A
1*
#44000000
0*
#44500000
b1001 A
b10 6
1*
#45000000
0*
#45500000
b11 6
b11 B
b0 A
1*
#46000000
0*
#46500000
b1 A
b100 6
1*
#47000000
0*
#47500000
b101 6
b10 A
1*
#48000000
0*
#48500000
b11 A
b110 6
1*
#49000000
0*
#49500000
b111 6
b100 A
1*
#50000000
0*
#50500000
b101 A
b1000 6
1*
#51000000
0*
#51500000
b1001 6
b110 A
1*
#52000000
0*
#52500000
b111 A
b100 5
b0 6
1*
#53000000
0*
#53500000
b1 6
b1000 A
1*
#54000000
0*
#54500000
b1001 A
b10 6
1*
#55000000
0*
#55500000
b11 6
b100 B
b0 A
1*
#56000000
0*
#56500000
b1 A
b100 6
1*
#57000000
0*
#57500000
b101 6
b10 A
1*
#58000000
0*
#58500000
b11 A
b110 6
1*
#59000000
0*
#59500000
b111 6
b100 A
1*
#60000000
0*
#60500000
b101 A
b1000 6
1*
#61000000
0*
#61500000
b1001 6
b110 A
1*
#62000000
0*
#62500000
b111 A
b101 5
b0 6
1*
#63000000
0*
#63500000
b1 6
b1000 A
1*
#64000000
0*
#64500000
b1001 A
b10 6
1*
#65000000
0*
#65500000
b11 6
b101 B
b0 A
1*
#66000000
0*
#66500000
b1 A
b100 6
1*
#67000000
0*
#67500000
b101 6
b10 A
1*
#68000000
0*
#68500000
b11 A
b110 6
1*
#69000000
0*
#69500000
b111 6
b100 A
1*
#70000000
0*
#70500000
b101 A
b1000 6
1*
#71000000
0*
#71500000
b1001 6
b110 A
1*
#72000000
0*
#72500000
b111 A
b110 5
b0 6
1*
#73000000
0*
#73500000
b1 6
b1000 A
1*
#74000000
0*
#74500000
b1001 A
b10 6
1*
#75000000
0*
#75500000
b11 6
b110 B
b0 A
1*
#76000000
0*
#76500000
b1 A
1!
1#
b100 6
1*
#77000000
0*
#77500000
b101 6
b10 A
1*
#78000000
0*
#78500000
b11 A
b110 6
1*
#79000000
0*
#79500000
b111 6
b100 A
1*
#80000000
0*
#80500000
b101 A
b1000 6
1*
#81000000
0*
#81500000
b1001 6
b110 A
1*
#82000000
0*
#82500000
b111 A
b111 5
b1000001 %
b1000001 7
b0 6
1*
#83000000
0*
#83500000
b1 6
b1000 A
1*
#84000000
0*
#84500000
b1001 A
b10 6
1*
#85000000
0*
#85500000
b11 6
b111 B
b0 A
1*
#86000000
0*
#86500000
b1 A
0!
0#
b100 6
1*
#87000000
0*
#87500000
b101 6
b10 A
1*
#88000000
0*
#88500000
b11 A
b110 6
1*
#89000000
0*
#89500000
b111 6
b100 A
1*
#90000000
0*
#90500000
b101 A
b1000 6
1*
#91000000
0*
#91500000
b1001 6
b110 A
1*
#92000000
0*
#92500000
b111 A
b11 8
b0 5
b0 6
1*
#93000000
0*
#93500000
b1 6
b1000 A
1*
#94000000
0*
#94500000
b1001 A
b10 6
1*
#95000000
0*
#95500000
b11 6
b11 D
b0 B
b0 A
1*
#96000000
0*
#96500000
b1 A
1!
1#
b100 6
1*
#97000000
0*
#97500000
b101 6
b10 A
1*
#98000000
0*
#98500000
b11 A
b110 6
1*
#99000000
0*
#99500000
b111 6
b100 A
1*
#100000000
0*
#100500000
b101 A
b1000 6
1*
#101000000
0*
#101500000
b1001 6
b110 A
1*
#102000000
0*
#102500000
b1 /
b111 A
b0 8
1$
0&
b0 6
1*
#103000000
0*
#103500000
0$
b1000 A
1*
#104000000
0*
#104500000
b1001 A
1*
#105000000
0*
#105500000
b1010101 ,
b1010101 9
b0 D
0"
b0 A
b1010101 E
1*
#106000000
0*
#106500000
b1 D
1"
b1010101 C
1-
1*
#107000000
0*
#107500000
b1 A
0!
0#
0-
1*
#108000000
0*
#108500000
b10 A
b1 8
1&
1*
#109000000
0*
#109500000
b1 6
b11 A
1*
#110000000
0*
#110500000
b100 A
b10 6
1*
#111000000
0*
#111500000
b11 6
b101 A
1*
#112000000
0*
#112500000
b110 A
b100 6
1*
#113000000
0*
#113500000
b10 8
b0 6
b111 A
1*
#114000000
0*
#114500000
b1000 A
b1 6
1*
#115000000
0*
#115500000
b10 6
b1001 A
1*
#116000000
0*
#116500000
b10 D
b0 A
b11 6
1*
#117000000
0*
#117500000
b100 6
b1 A
1!
1#
1*
#118000000
0*
#118500000
b10 A
b101 6
1*
#119000000
0*
#119500000
b110 6
b11 A
1*
#120000000
0*
#120500000
b100 A
b111 6
1*
#121000000
0*
#121500000
b1000 6
b101 A
1*
#122000000
0*
#122500000
b110 A
b1001 6
1*
#123000000
0*
#123500000
b1 5
b0 6
b111 A
1*
#124000000
0*
#124500000
b1000 A
b1 6
1*
#125000000
0*
#125500000
b10 6
b1001 A
1*
#126000000
0*
#126500000
b1 B
b0 A
b11 6
1*
#127000000
0*
#127500000
b100 6
b1 A
0!
0#
1*
#128000000
0*
#128500000
b10 A
b101 6
1*
#129000000
0*
#129500000
b110 6
b11 A
1*
#130000000
0*
#130500000
b100 A
b111 6
1*
#131000000
0*
#131500000
b1000 6
b101 A
1*
#132000000
0*
#132500000
b110 A
b1001 6
1*
#133000000
0*
#133500000
b10 5
b0 6
b111 A
1*
#134000000
0*
#134500000
b1000 A
b1 6
1*
#135000000
0*
#135500000
b10 6
b1001 A
1*
#136000000
0*
#136500000
b10 B
b0 A
b11 6
1*
#137000000
0*
#137500000
b100 6
b1 A
1!
1#
1*
#138000000
0*
#138500000
b10 A
b101 6
1*
#139000000
0*
#139500000
b110 6
b11 A
1*
#140000000
0*
#140500000
b100 A
b111 6
1*
#141000000
0*
#141500000
b1000 6
b101 A
1*
#142000000
0*
#142500000
b110 A
b1001 6
1*
#143000000
0*
#143500000
b11 5
b1000101 %
b1000101 7
b0 6
b111 A
1*
#144000000
0*
#144500000
b1000 A
b1 6
1*
#145000000
0*
#145500000
b10 6
b1001 A
1*
#146000000
0*
#146500000
b11 B
b0 A
b11 6
1*
#147000000
0*
#147500000
b100 6
b1 A
0!
0#
1*
#148000000
0*
#148500000
b10 A
b101 6
1*
#149000000
0*
#149500000
b110 6
b11 A
1*
#150000000
0*
#150500000
b100 A
b111 6
1*
#151000000
0*
#151500000
b1000 6
b101 A
1*
#152000000
0*
#152500000
b110 A
b1001 6
1*
#153000000
0*
#153500000
b100 5
b0 6
b111 A
1*
#154000000
0*
#154500000
b1000 A
b1 6
1*
#155000000
0*
#155500000
b10 6
b1001 A
1*
#156000000
0*
#156500000
b100 B
b0 A
b11 6
1*
#157000000
0*
#157500000
b100 6
b1 A
1!
1#
1*
#158000000
0*
#158500000
b10 A
b101 6
1*
#159000000
0*
#159500000
b110 6
b11 A
1*
#160000000
0*
#160500000
b100 A
b111 6
1*
#161000000
0*
#161500000
b1000 6
b101 A
1*
#162000000
0*
#162500000
b110 A
b1001 6
1*
#163000000
0*
#163500000
b101 5
b1010101 %
b1010101 7
b0 6
b111 A
1*
#164000000
0*
#164500000
b1000 A
b1 6
1*
#165000000
0*
#165500000
b10 6
b1001 A
1*
#166000000
0*
#166500000
b101 B
b0 A
b11 6
1*
#167000000
0*
#167500000
b100 6
b1 A
0!
0#
1*
#168000000
0*
#168500000
b10 A
b101 6
1*
#169000000
0*
#169500000
b110 6
b11 A
1*
#170000000
0*
#170500000
b100 A
b111 6
1*
#171000000
0*
#171500000
b1000 6
b101 A
1*
#172000000
0*
#172500000
b110 A
b1001 6
1*
#173000000
0*
#173500000
b110 5
b0 6
b111 A
1*
#174000000
0*
#174500000
b1000 A
b1 6
1*
#175000000
0*
#175500000
b10 6
b1001 A
1*
#176000000
0*
#176500000
b110 B
b0 A
b11 6
1*
#177000000
0*
#177500000
b100 6
b1 A
1!
1#
1*
#178000000
0*
#178500000
b10 A
b101 6
1*
#179000000
0*
#179500000
b110 6
b11 A
1*
#180000000
0*
#180500000
b100 A
b111 6
1*
#181000000
0*
#181500000
b1000 6
b101 A
1*
#182000000
0*
#182500000
b110 A
b1001 6
1*
#183000000
0*
#183500000
b111 5
b0 6
b111 A
1*
#184000000
0*
#184500000
b1000 A
b1 6
1*
#185000000
0*
#185500000
b10 6
b1001 A
1*
#186000000
0*
#186500000
b111 B
b0 A
b11 6
1*
#187000000
0*
#187500000
b100 6
b1 A
0!
0#
1*
#188000000
0*
#188500000
b10 A
b101 6
1*
#189000000
0*
#189500000
b110 6
b11 A
1*
#190000000
0*
#190500000
b100 A
b111 6
1*
#191000000
0*
#191500000
b1000 6
b101 A
1*
#192000000
0*
#192500000
b110 A
b1001 6
1*
#193000000
0*
#193500000
b11 8
b0 5
b0 6
b111 A
1*
#194000000
0*
#194500000
b1000 A
b1 6
1*
#195000000
0*
#195500000
b10 6
b1001 A
1*
#196000000
0*
#196500000
b11 D
b0 B
b0 A
b11 6
1*
#197000000
0*
#197500000
b100 6
b1 A
1!
1#
1*
#198000000
0*
#198500000
b10 A
b101 6
1*
#199000000
0*
#199500000
b110 6
b11 A
1*
#200000000
0*
#200500000
b100 A
b111 6
1*
#201000000
0*
#201500000
b1000 6
b101 A
1*
#202000000
0*
#202500000
b110 A
b1001 6
1*
#203000000
0*
#203500000
b10 /
b0 8
1$
0&
b0 6
b111 A
1*
#204000000
0*
#204500000
b1000 A
0$
1*
#205000000
0*
#205500000
b1001 A
1*
#206000000
0*
#206500000
b10101010 ,
b10101010 9
b0 D
0"
b0 A
b10101010 E
1*
#207000000
0*
#207500000
b1 D
1"
b10101010 C
1-
1*
#208000000
0*
#208500000
b1 A
0!
0#
0-
1*
#209000000
0*
#209500000
b1 8
1&
b10 A
1*
#210000000
0*
#210500000
b11 A
b1 6
1*
#211000000
0*
#211500000
b10 6
b100 A
1*
#212000000
0*
#212500000
b101 A
b11 6
1*
#213000000
0*
#213500000
b100 6
b110 A
1*
#214000000
0*
#214500000
b111 A
b10 8
b0 6
1*
#215000000
0*
#215500000
b1 6
b1000 A
1*
#216000000
0*
#216500000
b1001 A
b10 6
1*
#217000000
0*
#217500000
b11 6
b10 D
b0 A
1*
#218000000
0*
#218500000
b1 A
b100 6
1*
#219000000
0*
#219500000
b101 6
b10 A
1*
#220000000
0*
#220500000
b11 A
b110 6
1*
#221000000
0*
#221500000
b111 6
b100 A
1*
#222000000
0*
#222500000
b101 A
b1000 6
1*
#223000000
0*
#223500000
b1001 6
b110 A
1*
#224000000
0*
#224500000
b111 A
b1 5
b1010100 %
b1010100 7
b0 6
1*
#225000000
0*
#225500000
b1 6
b1000 A
1*
#226000000
0*
#226500000
b1001 A
b10 6
1*
#227000000
0*
#227500000
b11 6
b1 B
b0 A
1*
#228000000
0*
#228500000
b1 A
1!
1#
b100 6
1*
#229000000
0*
#229500000
b101 6
b10 A
1*
#230000000
0*
#230500000
b11 A
b110 6
1*
#231000000
0*
#231500000
b111 6
b100 A
1*
#232000000
0*
#232500000
b101 A
b1000 6
1*
#233000000
0*
#233500000
b1001 6
b110 A
1*
#234000000
0*
#234500000
b111 A
b10 5
b1010110 %
b1010110 7
b0 6
1*
#235000000
0*
#235500000
b1 6
b1000 A
1*
#236000000
0*
#236500000
b1001 A
b10 6
1*
#237000000
0*
#237500000
b11 6
b10 B
b0 A
1*
#238000000
0*
#238500000
b1 A
0!
0#
b100 6
1*
#239000000
0*
#239500000
b101 6
b10 A
1*
#240000000
0*
#240500000
b11 A
b110 6
1*
#241000000
0*
#241500000
b111 6
b100 A
1*
#242000000
0*
#242500000
b101 A
b1000 6
1*
#243000000
0*
#243500000
b1001 6
b110 A
1*
#244000000
0*
#244500000
b111 A
b11 5
b1010010 %
b1010010 7
b0 6
1*
#245000000
0*
#245500000
b1 6
b1000 A
1*
#246000000
0*
#246500000
b1001 A
b10 6
1*
#247000000
0*
#247500000
b11 6
b11 B
b0 A
1*
#248000000
0*
#248500000
b1 A
1!
1#
b100 6
1*
#249000000
0*
#249500000
b101 6
b10 A
1*
#250000000
0*
#250500000
b11 A
b110 6
1*
#251000000
0*
#251500000
b111 6
b100 A
1*
#252000000
0*
#252500000
b101 A
b1000 6
1*
#253000000
0*
#253500000
b1001 6
b110 A
1*
#254000000
0*
#254500000
b111 A
b100 5
b1011010 %
b1011010 7
b0 6
1*
#255000000
0*
#255500000
b1 6
b1000 A
1*
#256000000
0*
#256500000
b1001 A
b10 6
1*
#257000000
0*
#257500000
b11 6
b100 B
b0 A
1*
#258000000
0*
#258500000
b1 A
0!
0#
b100 6
1*
#259000000
0*
#259500000
b101 6
b10 A
1*
#260000000
0*
#260500000
b11 A
b110 6
1*
#261000000
0*
#261500000
b111 6
b100 A
1*
#262000000
0*
#262500000
b101 A
b1000 6
1*
#263000000
0*
#263500000
b1001 6
b110 A
1*
#264000000
0*
#264500000
b111 A
b101 5
b1001010 %
b1001010 7
b0 6
1*
#265000000
0*
#265500000
b1 6
b1000 A
1*
#266000000
0*
#266500000
b1001 A
b10 6
1*
#267000000
0*
#267500000
b11 6
b101 B
b0 A
1*
#268000000
0*
#268500000
b1 A
1!
1#
b100 6
1*
#269000000
0*
#269500000
b101 6
b10 A
1*
#270000000
0*
#270500000
b11 A
b110 6
1*
#271000000
0*
#271500000
b111 6
b100 A
1*
#272000000
0*
#272500000
b101 A
b1000 6
1*
#273000000
0*
#273500000
b1001 6
b110 A
1*
#274000000
0*
#274500000
b111 A
b110 5
b1101010 %
b1101010 7
b0 6
1*
#275000000
0*
#275500000
b1 6
b1000 A
1*
#276000000
0*
#276500000
b1001 A
b10 6
1*
#277000000
0*
#277500000
b11 6
b110 B
b0 A
1*
#278000000
0*
#278500000
b1 A
0!
0#
b100 6
1*
#279000000
0*
#279500000
b101 6
b10 A
1*
#280000000
0*
#280500000
b11 A
b110 6
1*
#281000000
0*
#281500000
b111 6
b100 A
1*
#282000000
0*
#282500000
b101 A
b1000 6
1*
#283000000
0*
#283500000
b1001 6
b110 A
1*
#284000000
0*
#284500000
b111 A
b111 5
b101010 %
b101010 7
b0 6
1*
#285000000
0*
#285500000
b1 6
b1000 A
1*
#286000000
0*
#286500000
b1001 A
b10 6
1*
#287000000
0*
#287500000
b11 6
b111 B
b0 A
1*
#288000000
0*
#288500000
b1 A
1!
1#
b100 6
1*
#289000000
0*
#289500000
b101 6
b10 A
1*
#290000000
0*
#290500000
b11 A
b110 6
1*
#291000000
0*
#291500000
b111 6
b100 A
1*
#292000000
0*
#292500000
b101 A
b1000 6
1*
#293000000
0*
#293500000
b1001 6
b110 A
1*
#294000000
0*
#294500000
b111 A
b11 8
b0 5
b10101010 %
b10101010 7
b0 6
1*
#295000000
0*
#295500000
b1 6
b1000 A
1*
#296000000
0*
#296500000
b1001 A
b10 6
1*
#297000000
0*
#297500000
b11 6
b11 D
b0 B
b0 A
1*
#298000000
0*
#298500000
b1 A
b100 6
1*
#299000000
0*
#299500000
b101 6
b10 A
1*
#300000000
0*
#300500000
b11 A
b110 6
1*
#301000000
0*
#301500000
b111 6
b100 A
1*
#302000000
0*
#302500000
b101 A
b1000 6
1*
#303000000
0*
#303500000
b1001 6
b110 A
1*
#304000000
0*
#304500000
b11 /
b111 A
b0 8
1$
0&
b0 6
1*
#305000000
0*
#305500000
0$
b1000 A
1*
#306000000
0*
#306500000
b1001 A
1*
#307000000
0*
#307500000
b0 ,
b0 9
b0 D
0"
b0 A
b0 E
1*
#308000000
0*
#308500000
b1 D
1"
b0 C
1-
1*
#309000000
0*
#309500000
b1 A
0!
0#
0-
1*
#310000000
0*
#310500000
b10 A
b1 8
1&
1*
#311000000
0*
#311500000
b1 6
b11 A
1*
#312000000
0*
#312500000
b100 A
b10 6
1*
#313000000
0*
#313500000
b11 6
b101 A
1*
#314000000
0*
#314500000
b110 A
b100 6
1*
#315000000
0*
#315500000
b10 8
b0 6
b111 A
1*
#316000000
0*
#316500000
b1000 A
b1 6
1*
#317000000
0*
#317500000
b10 6
b1001 A
1*
#318000000
0*
#318500000
b10 D
b0 A
b11 6
1*
#319000000
0*
#319500000
b100 6
b1 A
1*
#320000000
0*
#320500000
b10 A
b101 6
1*
#321000000
0*
#321500000
b110 6
b11 A
1*
#322000000
0*
#322500000
b100 A
b111 6
1*
#323000000
0*
#323500000
b1000 6
b101 A
1*
#324000000
0*
#324500000
b110 A
b1001 6
1*
#325000000
0*
#325500000
b1 5
b0 6
b111 A
1*
#326000000
0*
#326500000
b1000 A
b1 6
1*
#327000000
0*
#327500000
b10 6
b1001 A
1*
#328000000
0*
#328500000
b1 B
b0 A
b11 6
1*
#329000000
0*
#329500000
b100 6
b1 A
1*
#330000000
0*
#330500000
b10 A
b101 6
1*
#331000000
0*
#331500000
b110 6
b11 A
1*
#332000000
0*
#332500000
b100 A
b111 6
1*
#333000000
0*
#333500000
b1000 6
b101 A
1*
#334000000
0*
#334500000
b110 A
b1001 6
1*
#335000000
0*
#335500000
b10 5
b10101000 %
b10101000 7
b0 6
b111 A
1*
#336000000
0*
#336500000
b1000 A
b1 6
1*
#337000000
0*
#337500000
b10 6
b1001 A
1*
#338000000
0*
#338500000
b10 B
b0 A
b11 6
1*
#339000000
0*
#339500000
b100 6
b1 A
1*
#340000000
0*
#340500000
b10 A
b101 6
1*
#341000000
0*
#341500000
b110 6
b11 A
1*
#342000000
0*
#342500000
b100 A
b111 6
1*
#343000000
0*
#343500000
b1000 6
b101 A
1*
#344000000
0*
#344500000
b110 A
b1001 6
1*
#345000000
0*
#345500000
b11 5
b0 6
b111 A
1*
#346000000
0*
#346500000
b1000 A
b1 6
1*
#347000000
0*
#347500000
b10 6
b1001 A
1*
#348000000
0*
